{
  "enabled": true,
  "show_after": "2025-03-20",
  "force_update": false,
  "title": "Update Available",
  "message": "A new version is ready. Please update for best experience.
join my channel for more @Android_AppsX",
  "link_text": "Join Our Channel",
  "link_url": "https://t.me/android_appsx",
  "buttons": [
    {
      "text": "Update Now",
      "action": "url",
      "target": "https://dr-venture.com/apks/android%20tools/AppLinked-v1.0.7.apk",
      "style": "primary"
    },
    {
      "text": "Later",
      "action": "dismiss",
      "style": "secondary"
    }
  ]
}
